sample/__init__.py
safeutils-0.0.1.dist-info/LICENSE.md
safeutils-0.0.1.dist-info/METADATA
safeutils-0.0.1.dist-info/WHEEL
safeutils-0.0.1.dist-info/top_level.txt
safeutils-0.0.1.dist-info/RECORD
