Metadata-Version: 2.1
Name: safeutils
Version: 0.0.1
Summary: SafeUtils: Native MacOS, Linux and Windows desktop application with 110+ carefully crafted tools for yours and your teams everyday work with sensitive data in various formats.
Author-email: Wiktor Plaga <wiktor.plaga@tzif.io>
Maintainer-email: Wiktor Plaga <wiktor.plaga@tzif.io>
License: See: [https://safeutils.com/terms](https://safeutils.com/terms).
Project-URL: Homepage, https://safeutils.com
Project-URL: Bug Reports, https://safeutils.com/contact
Project-URL: Funding, https://safeutils.com/pricing
Project-URL: Say Thanks!, https://safeutils.com/review
Project-URL: Source, https://github.com/safe-utils/.github
Keywords: developer-tools,data-security,data-privacy
Classifier: Development Status :: 5 - Production/Stable
Classifier: Operating System :: MacOS
Classifier: Operating System :: Microsoft :: Windows
Classifier: Operating System :: Unix
Classifier: Intended Audience :: Developers
Classifier: Intended Audience :: End Users/Desktop
Classifier: Intended Audience :: Information Technology
Classifier: Intended Audience :: System Administrators
Classifier: License :: Other/Proprietary License
Classifier: Natural Language :: English
Classifier: Programming Language :: JavaScript
Classifier: Programming Language :: Rust
Classifier: Programming Language :: Python :: 3
Classifier: Programming Language :: Python :: 3.8
Classifier: Programming Language :: Python :: 3.9
Classifier: Programming Language :: Python :: 3.10
Classifier: Programming Language :: Python :: 3.11
Classifier: Programming Language :: Python :: 3.12
Classifier: Programming Language :: Python :: 3 :: Only
Classifier: Topic :: Security
Classifier: Topic :: Software Development
Requires-Python: >=3.8
License-File: LICENSE.md
Provides-Extra: dev
Provides-Extra: test
